LICENSE
README.md
setup.py
biodive/AnchorKmer.py
biodive/Config.py
biodive/__init__.py
biodive/bio.py
biodive/debruijn.py
biodive/io.py
biodive/jaccard.py
biodive/mystats.py
biodive/plots.py
biodive/poibin.py
biodive/simulations.py
biodive.egg-info/PKG-INFO
biodive.egg-info/SOURCES.txt
biodive.egg-info/dependency_links.txt
biodive.egg-info/requires.txt
biodive.egg-info/top_level.txt