Metadata-Version: 2.1
Name: biodive
Version: 0.1.2
Summary: Discovery of k-mer sequences associated with high rates of sequence diversification.
Home-page: https://github.com/jordiabante/biodive
Author: Jordi Abante
Author-email: jordiabante@protonmail.com
License: Apache License 2.0
Keywords: python,horizontal gene transfer,mobile genetic elements,crispr,diversity-generating mechanisms
Platform: UNKNOWN
